glyco/__init__.py
glyco/glucose.py
glyco/meals.py
glyco/privacy.py
glyco/utils.py
glyco-0.0.1.dist-info/licenses/LICENSE
glyco-0.0.1.dist-info/METADATA
glyco-0.0.1.dist-info/WHEEL
glyco-0.0.1.dist-info/entry_points.txt
glyco-0.0.1.dist-info/top_level.txt
glyco-0.0.1.dist-info/RECORD
