Metadata-Version: 2.4
Name: glyco
Version: 0.0.1
Summary: Read and analyse continuous glucose monitoring data
Author-email: Ismail Elouafiq <contact@ismail.bio>
License: MIT License
Project-URL: Homepage, https://github.com/nidhog/glyco
Project-URL: Visual, https://ismail.bio/glyco
Project-URL: Author, https://ismail.bio
Keywords: glucose,glyco,cgm,continuous glucose monitoring,health,healthcare
Classifier: License :: OSI Approved :: MIT License
Classifier: Programming Language :: Python
Classifier: Programming Language :: Python :: 3
Classifier: Development Status :: 2 - Pre-Alpha
Classifier: Intended Audience :: Healthcare Industry
Classifier: Topic :: Scientific/Engineering :: Bio-Informatics
Requires-Python: >=3.10
License-File: LICENSE
Requires-Dist: pandas
Requires-Dist: scipy
Requires-Dist: numpy
Requires-Dist: matplotlib
Requires-Dist: matplotlib-inline
Requires-Dist: rich
Requires-Dist: seaborn
Provides-Extra: dev
Requires-Dist: black; extra == "dev"
Requires-Dist: bumpver; extra == "dev"
Requires-Dist: isort; extra == "dev"
Requires-Dist: pip-tools; extra == "dev"
Requires-Dist: pytest; extra == "dev"
Dynamic: license-file
